{"date":1770739420955,"name":"blakearchive/data","url":"https://github.com/blakearchive/data","desc":"-","files":["teicontent/biography.xml","teicontent/clackland.xml","teicontent/clashmolean.xml","teicontent/clbirmingham.xml","teicontent/clbodley.xml","teicontent/clboston.xml","teicontent/clbritishlibrary.xml","teicontent/clbritishmuseum.xml","teicontent/clbrooklyn.xml","teicontent/clcincinnati.xml","teicontent/clcornwall.xml","teicontent/clessick.xml","teicontent/clfitzwilliam.xml","teicontent/clfogg.xml","teicontent/clgetty.xml","teicontent/clglasgow.xml","teicontent/clhoughton.xml","teicontent/clhuntington.xml","teicontent/cllc.xml","teicontent/cllouvre.xml","teicontent/clmead.xml","teicontent/clmet.xml","teicontent/clminneapolis.xml","teicontent/clmorgan.xml","teicontent/clngadc.xml","teicontent/clngs.xml","teicontent/clngvic.xml","teicontent/clnypl.xml","teicontent/clphiladelphia.xml","teicontent/clrisd.xml","teicontent/clrosenbach.xml","teicontent/cltate.xml","teicontent/clvanda.xml","teicontent/clvictoria.xml","teicontent/clwhitworth.xml","teicontent/clycba.xml","teicontent/collectionlists.xml","teicontent/general.xml","teicontent/glossary.xml","teicontent/illum.xml","teicontent/specific.xml","works/illum.xml","works/specific.xml"],"langs":[]}