{"date":1590816600635,"name":"adunning/bedes-bible","url":"https://github.com/adunning/bedes-bible","desc":"Bede's Bible: An Edition of the Latin Vulgate from the Codex Amiatinus","files":["text/0949v-corintheos-i.xml","text/0938r-romanos.xml","text/1016v-apocalypsis-iohannis.xml","text/0050r-exodus-cap.xml","text/0009v-genesis-cap.xml","text/0948v-corintheos-i-cap.xml","text/0832v-marcum.xml","text/0985r-thessalonicenses-ii.xml","text/0881v-iohannem-cap.xml","text/0904r-actus-apostolorum-cap.xml","text/0650vb-duodecim-cap.xml","text/0883r-iohannem.xml","text/0004r-contents.xml","text/1009v-petri-ii.xml","text/0275r-malachim-cap.xml","text/0803r-mattheum-cap.xml","text/0990r-timotheum-ii.xml","text/0590rb-hiezechiel-cap.xml","text/0905v-actus-apostolorum.xml","text/0805r-mattheum.xml","text/0219r-samuhel-cap.xml","text/0852r-lucam.xml","text/0982v-thessalonicenses-i.xml","text/0979v-colossenes.xml","text/1003v-iacobi.xml","text/0496v-esias-cap.xml","text/0976v-philippenses.xml","text/0536r-hieremias-cap.xml","text/0849v-lucam-cap.xml","text/0986v-timotheum-i.xml","text/1012r-iohannis-i.xml","text/1006v-petri-i.xml","text/0968v-galatas.xml","text/0972v-ephesios.xml","text/0936r-epistulae-cap.xml","text/0960v-corintheos-ii.xml","text/0995r-hebraeos.xml","text/0976r-philippenses-cap.xml","text/0986r-timotheum-i-cap.xml","text/0972r-ephesios-cap.xml","text/0993v-philemonem.xml","text/0982r-thessalonicenses-i-cap.xml","text/0989v-timotheum-ii-cap.xml","text/1014v-iohannis-ii.xml","text/0849r-lucam-prol.xml","text/0849r-lucam-praef.xml","text/0634r-danihel-cap.xml","text/0086r-leuiticus-cap.xml","text/0460r-ecclesiasticum-cap.xml","text/0709r-iudith-cap.xml","text/0831ra-marcum-praef.xml","text/1015r-iohannis-iii.xml","text/1011v-iohannis-i-cap.xml","text/0436v-ecclesiastes-cap.xml","text/1015v-iudae-cap.xml","text/0802v-mattheum-prol.xml","text/0979r-colossenes-cap.xml","text/1006v-petri-i-cap.xml","text/0992r-titum-cap.xml","text/0802v-mattheum-praef.xml","text/0831r-marcum-prol.xml","text/0881r-iohannem-praef.xml","text/0419rb-prouerbia-cap.xml"],"langs":["lat"]}