{"date":1590816600998,"name":"pingtzuchu/ConfucainClassics","url":"https://github.com/pingtzuchu/ConfucainClassics","desc":"Confucain Classics Project","files":["data/kr1/KR1d0080.xml","data/kr1/KR1a0157.xml","data/kr1/KR1a0045.xml","data/list.xml","data/kr1/KR1e0072.xml","data/kr1/KR1e0014.xml","data/kr1/KR1b0008.xml","data/kr1/KR1j0006.xml","data/kr1/KR1a0067.xml","data/kr1/KR1a0035.xml","data/kr1/KR1a0063.xml","data/kr1/KR1d0056.xml","data/kr1/KR1b0050.xml","data/kr1/KR1e0023.xml","data/kr1/KR1d0023.xml","data/kr1/KR1d0092.xml","data/kr1/KR1a0137.xml","data/kr1/KR1e0059.xml","data/kr1/KR1e0110.xml","data/kr1/KR1b0032.xml","data/kr1/KR1a0039.xml","data/kr1/KR1a0129.xml","data/kr1/KR1a0094.xml","data/kr1/KR1d0062.xml","data/kr1/KR1a0085.xml","data/kr1/KR1d0079.xml","data/kr1/KR1e0015.xml","data/kr1/KR1a0132.xml","data/kr1/KR1d0008.xml","data/kr1/KR1d0083.xml","data/kr1/KR1e0027.xml","data/kr1/KR1d0090.xml","data/kr1/KR1d0024.xml","data/kr1/KR1d0046.xml","data/kr1/KR1e0067.xml","data/kr1/KR1g0010.xml","data/kr1/KR1b0028.xml","data/kr1/KR1d0089.xml","data/kr1/KR1b0056.xml","data/kr1/KR1a0013.xml","data/kr1/KR1j0002.xml","data/kr1/KR1b0033.xml","data/kr1/KR1a0099.xml","data/kr1/KR1j0031.xml","data/kr1/KR1b0043.xml","data/kr1/KR1c0011.xml","data/kr1/KR1a0065.xml","data/kr1/KR1h0005.xml","data/kr1/KR1c0038.xml","data/kr1/KR1j0010.xml","data/kr1/KR1a0068.xml","data/kr1/KR1c0062.xml","data/kr1/KR1a0029.xml","data/kr1/KR1c0066.xml","data/kr1/KR1e0115.xml","data/kr1/KR1a0106.xml","data/kr1/KR1f0004.xml","data/kr1/KR1g0017.xml","data/kr1/KR1d0091.xml","data/kr1/KR1g0005.xml","data/kr1/KR1e0082.xml","data/kr1/KR1g0014.xml","data/kr1/KR1g0018.xml","data/kr1/KR1e0030.xml","data/kr1/KR1a0019.xml","data/kr1/KR1d0011.xml","data/kr1/KR1a0156.xml","data/kr1/KR1b0059.xml","data/kr1/KR1c0026.xml","data/kr1/KR1g0006.xml","data/kr1/KR1b0023.xml","data/kr1/KR1a0109.xml","data/kr1/KR1g0013.xml","data/kr1/KR1b0038.xml","data/kr1/KR1a0072.xml","data/kr1/KR1a0009.xml","data/kr1/KR1d0036.xml","data/kr1/KR1e0026.xml","data/kr1/KR1e0077.xml","data/kr1/KR1g0007.xml","data/kr1/KR1a0014.xml","data/kr1/KR1d0081.xml","data/kr1/KR1a0093.xml","data/kr1/KR1a0144.xml","data/kr1/KR1d0088.xml","data/kr1/KR1d0048.xml","data/kr1/KR1a0052.xml","data/kr1/KR1e0029.xml","data/kr1/KR1a0005.xml","resources/css/tei_chinese.css","data/kr1/KR1d0043.xml","data/kr1/KR1e0020.xml","data/kr1/KR1f0002.xml"],"langs":[]}