{"date":1674035114982,"name":"nakamura196/genji_vue","url":"https://github.com/nakamura196/genji_vue","desc":"-","files":["static/data/tei/koui/01.xml","static/data/tei/koui/03.xml","static/data/tei/koui/05.xml","static/data/tei/koui/06.xml","static/data/tei/koui/07.xml","static/data/tei/koui/08.xml","static/data/tei/koui/09.xml","static/data/tei/koui/10.xml","static/data/tei/koui/11.xml","static/data/tei/yosano/01.xml","static/data/tei/yosano/02.xml","static/data/tei/yosano/03.xml","static/data/tei/yosano/04.xml","static/data/tei/yosano/05.xml","static/data/tei/yosano/06.xml","static/data/tei/yosano/07.xml","static/data/tei/yosano/08.xml","static/data/tei/yosano/09.xml","static/data/tei/yosano/10.xml","static/data/tei/yosano/11.xml","static/data/tei/yosano/12.xml","static/data/tei/yosano/13.xml","static/data/tei/yosano/14.xml","static/data/tei/yosano/15.xml","static/data/tei/yosano/16.xml","static/data/tei/yosano/17.xml","static/data/tei/yosano/18.xml","static/data/tei/yosano/19.xml","static/data/tei/yosano/20.xml","static/data/tei/yosano/21.xml","static/data/tei/yosano/22.xml","static/data/tei/yosano/23.xml","static/data/tei/yosano/24.xml","static/data/tei/yosano/25.xml","static/data/tei/yosano/26.xml","static/data/tei/yosano/27.xml","static/data/tei/yosano/28.xml","static/data/tei/yosano/29.xml","static/data/tei/yosano/30.xml","static/data/tei/yosano/31.xml","static/data/tei/yosano/32.xml","static/data/tei/yosano/33.xml","static/data/tei/yosano/34.xml","static/data/tei/yosano/35.xml","static/data/tei/yosano/36.xml","static/data/tei/yosano/37.xml","static/data/tei/yosano/38.xml","static/data/tei/yosano/39.xml","static/data/tei/yosano/40.xml","static/data/tei/yosano/41.xml","static/data/tei/yosano/42.xml","static/data/tei/yosano/43.xml","static/data/tei/yosano/44.xml","static/data/tei/yosano/45.xml","static/data/tei/yosano/46.xml","static/data/tei/yosano/47.xml","static/data/tei/yosano/48.xml","static/data/tei/yosano/49.xml","static/data/tei/yosano/50.xml","static/data/tei/yosano/51.xml","static/data/tei/yosano/52.xml","static/data/tei/yosano/53.xml","static/data/tei/yosano/54.xml","static/data/tei/yosano/55.xml","static/data/tei/yosano/56.xml"],"langs":[]}