{"date":1590816600992,"name":"papyri/sosol","url":"https://github.com/papyri/sosol","desc":"The Son of Suda On Line","files":["data/templates/tei-xl-psg.rng","app/models/identifier.rb","public/javascripts/formX.js","app/models/hgv_meta_identifier.rb","data/templates/tei-xl.rng","public/javascripts/meta.js","app/models/publication.rb","data/schemas/www.stoa.org/epidoc/dtd/6/tei-epidoc.dtd","app/helpers/tei-epidoc.dtd","data/xslt/translation/hgv-glossary.xml","data/templates/tei-xl-xsl.xsl"],"langs":["grc","deu","eng","fra","lat"]}