{"date":1667123362991,"name":"cschuwey/labruyere_ubs","url":"https://github.com/cschuwey/labruyere_ubs","desc":"-","files":["Mébirouk Chloé/Exercice 1","Clairvie/exercice 1","Mouillet/exercice 1","elise/exo1","MaryneSaunier/Exercice1","Aminata/Exercice 1","Alexis LN/Exercice 1","MathieuMRN/Exercice 1","Le Guellaud/Exercice 1","RIVRON/exercice 1","Plailly/exercice 1","lucieMention/Exercice 1","steven/exercice1","Mébirouk_Chloé/Femmes_61-81.xml","Marquet_Clairvie/Conversation_1-20.xml","Mouillet_Julie/Usages_1-20.xml","Vasselin_Elise/Grands_1-20.xml","Saunier_Marine/Ouvrages_33-53.xml","Ndiathie_Aminata/Jugements_32-52.xml","LeNeve_Alexis/Conversation_21-41.xml","Morin_Mathieu/Merite_20-40.xml","LeGuellaud_Enora/Cœur_1-20.xml","Rivron_Lisa/Cœur_29-49.xml","Plailly_Clara/Fortune_1-20.xml","Mention_Lucie/Jugements_1-20.xml","LeBlevec_Steven/Femmes_61-81.xml","Brassac_paul/Des Esprits Fort 1 a 20","Georget_Laureline/Du Coeur de 61 à 81","larroque_marine/de_la_societe_et_de_la_conversation_45_a_65","jade_lanthoen/de_quelques_usages","Kolodziej_Emma/DeLaCour_1à20","Gervraud_Emma/Du cœur de 21 à 28 et 50 à 60","Sarah_Kergourlay/Ouvrages_de_l_esprit_54-69","Bernardi_Clotilde/De_La_Mode","Caous_Audrey/Des Ouvrages de l'Esprit de 10 à 30","camille_collin/La chair 1-20","Janiak_Margot/Des biens de fortune 21-41","Fontaine-Demay Sarah/Des femmes 21-41","Collin_Margot/de la ville 1-20","test","LeBlevec_Steven/Femmes_40-60.xml","Saunier_Maryne","Amine_Nadir","Plailly_Clara/version 2","COSTIOU_Nicolas-Bruyere","COSTIOU_Nicolas-Bruyere.xml","Fontaine-Demay_Sarah/Femmes_21-41.xml","Lanthoen_Jade/de_quelques_usages.xml","Janiak_Margot/Biens_Fortune_21-41.xml","Collin_Margot/Ville_1-20.xml","Larroque_Marine/de_la_societe_et_de_la_conversation_45_a_65.xml","Kolodziej_Emma/DeLaCour_1-20.xml","Caous_Audrey/Ouvrages_de_l'Esprit_10-30.xml","Collin_Camille/Chaire_1-20.xml","Bernardi_Clotilde/De_La_Mode.xml","Georget_Laureline/Coeur_61-81.xml","Gervraud_Emma/Coeur21-28-50-60.xml","Brassac_paul/Travail_du_11_Octobre.xml","Brassac_paul/Des esprits fort 1 à 20.xml","Le Blevec_exercice 1","Mébirouk_Chloé/Devoir 1","LeGuellaud_Enora/Devoir 1 : teiHeader et exemplaires","Plailly_Clara/Travail TD3","Kolodziej_Emma/Devoir1_EmmaK.xml","Kergourlay_Sarah/Ouvrages_de_l_esprit_54-69","Brassac_Paul/Des esprits fort 1 à 20.xml","Schuwey_Christophe/Conversation_21-41.xml","Vasselin_Elise/teilabruyère3octEXO10OCT.xml","Plailly_Clara/Plailly_TD_11102022","Rivron_Lisa/labruyere_suite","Kolodziej_Emma/Devoir2.xml","Anissa_Chahboun/Les caractères de la Bruyère","Rivron_Lisa/labruyere_suite.xml","Vasselin_Elise/teilabruyère_version15oct.xml","COSTIOU-Nicolas","Plailly_Clara/Plailly_TD_17102022"],"langs":["fra","lat"]}