{"date":1602247789859,"name":"DHBern/DLPA2020","url":"https://github.com/DHBern/DLPA2020","desc":"Digital Literacy for the Performing Arts","files":["tei/testTEI.xml","tei/tei_all.rng","tei/transkribus/transkribus-output.xml","tei/example/tei_drama-example.rng","tei/example/TEI-example.xml","tei/TEI-template.xml","tei/vparrilla/TEI-template-vicente.xml","tei/zoep/tei_drama.rng","tei/zoep/TEI-zoe.xml","tei/maria/maria.xml","tei/lpugin/tei_drama-example.rng","tei/lpugin/TEI-lpugin.xml","tools/cetei/CETEI.js","tools/cetei/CETEIcean.css"],"langs":[]}