{"date":1590816600259,"name":"CDRH/data_castingnets","url":"https://github.com/CDRH/data_castingnets","desc":"Data Repository for Casting Digital Nets","files":["source/tei/cdn.land.letter.0002.xml","source/tei/cdn.land.letter.0004.xml","source/tei/cdn.land.letter.0009.xml","source/tei/cdn.land.letter.0006.xml","source/tei/cdn.water.fishdays.0002.xml","source/tei/cdn.land.letter.0005.xml","source/tei/cdn.land.letter.0007.xml","source/tei/cdn.land.letter.0001.xml","source/tei/cdn.water.boat.0035.xml","source/tei/cdn.land.refuge.0002.xml","source/tei/cdn.land.game.0027.xml","source/tei/cdn.land.resort.0015.xml","source/tei/cdn.land.game.0012.xml","source/tei/cdn.land.goodroads.0010.xml","source/tei/cdn.land.game.0031.xml","source/tei/cdn.land.resort.0011.xml","source/tei/cdn.land.refuge.0003.xml","source/tei/cdn.water.boat.0005.xml","source/tei/cdn.land.resort.0024.xml","source/tei/cdn.land.game.0005.xml","source/tei/cdn.water.lake.0001.xml","source/tei/cdn.land.refuge.0001.xml","source/tei/cdn.land.game.0002.xml","source/tei/cdn.water.lake.0007.xml","source/tei/cdn.land.game.0029.xml","source/tei/cdn.land.law.0017.xml","source/tei/cdn.water.boat.0004.xml","source/tei/cdn.land.law.0004.xml","source/tei/cdn.land.resort.0023.xml","source/tei/cdn.land.law.0011.xml","source/tei/cdn.land.farmersinstitute.0008.xml","source/tei/cdn.land.game.0010.xml","source/tei/cdn.land.goodroads.0014.xml","source/tei/cdn.water.boat.0024.xml"],"langs":[]}