{"date":1590816600839,"name":"ParkerWeb/descMD","url":"https://github.com/ParkerWeb/descMD","desc":"Descriptive Metadata for Parker on the Web","files":["split-xmls/description/170.xml","split-xmls/description/119.xml","split-xmls/description/396.xml","split-xmls/description/333.xml","split-xmls/description/426.xml","split-xmls/description/534.xml","split-xmls/description/461.xml","split-xmls/description/2II.xml","split-xmls/description/511.xml","split-xmls/description/345.xml","split-xmls/description/466.xml","split-xmls/description/153.xml","split-xmls/description/251.xml","split-xmls/description/473.xml","split-xmls/description/22.xml","split-xmls/description/51.xml","split-xmls/description/93.xml","split-xmls/description/114B.xml","split-xmls/description/111.xml","split-xmls/description/294.xml","split-xmls/description/232.xml","split-xmls/description/328.xml","split-xmls/description/304.xml","split-xmls/description/38.xml","split-xmls/description/425.xml","split-xmls/description/142.xml","split-xmls/description/137.xml","split-xmls/description/30.xml","split-xmls/description/171B.xml","split-xmls/description/114A.xml","split-xmls/description/100.xml","split-xmls/description/135.xml","split-xmls/description/460.xml","split-xmls/description/314.xml","split-xmls/description/424.xml","split-xmls/description/264.xml","split-xmls/description/199.xml","split-xmls/description/339.xml","split-xmls/description/509.xml","split-xmls/description/197A.xml","split-xmls/description/375.xml","split-xmls/description/326.xml","split-xmls/description/36.xml","split-xmls/description/485.xml","split-xmls/description/393.xml","split-xmls/description/130.xml","split-xmls/description/171A.xml","split-xmls/description/44.xml","split-xmls/description/373.xml","split-xmls/description/81.xml","split-xmls/description/411.xml","split-xmls/description/542.xml","split-xmls/description/206.xml","split-xmls/description/179.xml","split-xmls/description/419.xml","split-xmls/description/438.xml","split-xmls/description/201.xml","split-xmls/description/450.xml"],"langs":["lat","eng","enm","ell","ang"]}