{"date":1590816600993,"name":"ndlib/text-analysis-eebo","url":"https://github.com/ndlib/text-analysis-eebo","desc":"Prototype text analysis against the EEBO collection","files":["mather/xml/A50157.xml","baxter/xml/A26927.xml","baxter/xml/A27042.xml","baxter/xml/A26901.xml","etc/xsl/docx/to/teitodocx.xsl","baxter/xml/A27030.xml","baxter/xml/A26963.xml","baxter/xml/A26928.xml","etc/xsl/Test/test22.xml","baxter/xml/A26936.xml","baxter/xml/A27001.xml","shakespeare/xml/A11983.xml","baxter/xml/A26958.xml","etc/xsl/Test/expected-results/test33.rnc","etc/xsl/Test/expected-results/test34.rnc","etc/xsl/Test/expected-results/test35.rnc","shakespeare/xml/A12035.xml","baxter/xml/A26856.xml","etc/xsl/Test/expected-results/test15.odd.rnc","baxter/xml/A26854.xml","baxter/xml/A26895.xml","baxter/xml/A26929.xml","baxter/xml/A26939.xml","etc/xsl/profiles/iso/schema/teix.xsd","etc/xsl/Test/expected-results/test30.dtd","etc/xsl/Test/expected-results/test34.combined.json","baxter/xml/A27011.xml","baxter/xml/A26887.xml","baxter/xml/A26882.xml","baxter/xml/A26914.xml","baxter/xml/A27008.xml","baxter/xml/A76162.xml","shakespeare/xml/A11975.xml","etc/xsl/Test/test20.xml","etc/xsl/profiles/iso/schema/test3.xsl","etc/xsl/Test/testapp2.xml","etc/xsl/Test/expected-results/cocoatest2.xml","etc/xsl/Test/expected-results/test30.rnc","mather/xml/A50142.xml","shakespeare/xml/A11989.xml","mather/xml/A50164.xml","shakespeare/xml/A12040.xml","baxter/xml/A69538.xml","etc/xsl/Test/expected-results/test29.xml","etc/xsl/profiles/iso/latex/to.xsl","shakespeare/xml/A68931.xml","baxter/xml/A26869.xml","etc/xsl/Test/expected-results/test17.tei","etc/xsl/Test/test17.xml","etc/xsl/profiles/iso/isoutils.xsl","baxter/xml/A26934.xml","shakespeare/xml/A68727.xml","baxter/xml/A26870.xml","baxter/xml/A26948.xml","etc/xsl/rdf/crm.xsl","etc/xsl/epub/epub-common.xsl","etc/xsl/profiles/iso/schema/isotei-lite.rng","shakespeare/xml/A12043.xml","etc/xsl/Test/testdocx/MLIFinODDV5.xml","baxter/xml/A26975.xml","baxter/xml/A76214.xml","shakespeare/xml/A11959.xml","shakespeare/xml/A11991.xml","shakespeare/xml/A11981.xml","etc/xsl/Test/expected-results/test21.odd.rnc","etc/xsl/profiles/iso/schema/isotei-lite.xsd","etc/xsl/odds/odd2relax.xsl","etc/xsl/profiles/oxford/p4/from.xsl","etc/xsl/profiles/iso/schema/test2.xsl","etc/xsl/profiles/default/p4/from.xsl","etc/xsl/Test/expected-results/test38.xml","etc/xsl/profiles/iso/schema/ns1.xsd","etc/xsl/Test/expected-results/test.odd.html","baxter/xml/A26909.xml","baxter/xml/A27014.xml","etc/xsl/docx/from/docxtotei.xsl","etc/xsl/Test/expected-results/test34.odd.html","shakespeare/xml/A12024.xml","shakespeare/xml/A11966.xml","shakespeare/xml/A11994.xml","shakespeare/xml/A11974.xml","shakespeare/xml/A59497.xml","baxter/xml/A26896.xml","shakespeare/xml/A12010.xml","baxter/xml/A27028.xml","etc/xsl/profiles/iso/schema/isotei-odd.xsd","shakespeare/xml/A10726.xml","baxter/xml/A69536.xml","baxter/xml/A26957.xml","baxter/xml/A26964.xml","baxter/xml/A26871.xml","baxter/xml/A26960.xml","shakespeare/xml/A12017.xml","shakespeare/xml/A68726.xml","baxter/xml/A26868.xml","baxter/xml/A27036.xml","baxter/xml/A27063.xml","baxter/xml/A76181.xml","etc/xsl/Test/test-tree.xml","etc/xsl/common/common_linking.xsl","mather/xml/A50116.xml","baxter/xml/A26953.xml","etc/xsl/profiles/iso/schema/isotei.rnc","shakespeare/xml/A11988.xml","baxter/xml/A27061.xml","mather/xml/A50162.xml","shakespeare/xml/A11978.xml","etc/xsl/Documentation/teixsl.xml","baxter/xml/A27012.xml","baxter/xml/A27037.xml","etc/xsl/tools/oddbyexample.xsl","baxter/xml/A27003.xml","baxter/xml/A26976.xml","baxter/xml/A26987.xml","mather/xml/A50139.xml","baxter/xml/A26903.xml","baxter/xml/A26945.xml","etc/xsl/Test/test36.xml","etc/xsl/Test/expected-results/test11.xml","baxter/xml/A27038.xml","baxter/xml/A27068.xml","baxter/xml/A26998.xml","etc/xsl/Test/expected-results/test11a.xml","etc/xsl/profiles/iso/schema/isotei-odd.rnc","etc/xsl/Test/floating-text-notes-renum-b.xml","etc/xsl/Test/test12.xml","baxter/xml/A27048.xml","baxter/xml/A26983.xml","baxter/xml/A26859.xml","etc/xsl/profiles/iso/schema/isotei-odd.sch","etc/xsl/profiles/iso/schema/isotei.sch","baxter/xml/A26941.xml","etc/xsl/Test/expected-results/test15.odd.html","baxter/xml/A26897.xml","etc/xsl/Test/test32.xml","baxter/xml/A26982.xml","baxter/xml/A26911.xml","etc/xsl/Test/expected-results/test39.xml","shakespeare/xml/A12001.xml","baxter/xml/A27032.xml","shakespeare/xml/A11992.xml","baxter/xml/A26872.xml","etc/xsl/epub3/tei-to-epub3.xsl","etc/xsl/Test/test.xml","etc/xsl/epub/tei-to-epub.xsl","baxter/xml/A76168.xml","etc/xsl/Test/testp4.xml","etc/xsl/odds/guidelines.xsl","etc/xsl/odt/teitoodt.xsl","etc/xsl/profiles/iso/docx/to.xsl","etc/xsl/profiles/jtei/odt/odt.common.xsl","etc/xsl/profiles/iso/isotei-schema.xsl","etc/xsl/profiles/jtei/openedition/to.xsl","etc/xsl/profiles/jtei/pdf/to.xsl","baxter/xml/A26979.xml","mather/xml/A50154.xml","etc/xsl/Test/ms.xml","baxter/xml/A26980.xml","etc/xsl/html/html_param.xsl"],"langs":["eng","ava","lat","ell","srp","isl","cym","dan","lit","fro","heb","sqi"]}