{"date":1669290408958,"name":"nuntiaturberichte/nbr-pius-xi-data","url":"https://github.com/nuntiaturberichte/nbr-pius-xi-data","desc":"data repo for TEI edition data (Nuntiaturberichte Pius XI)","files":["TEI/editions/852-24-4.xml","TEI/editions/848-20-47.xml","TEI/editions/869-33-43.xml","TEI/editions/852-25-78.xml","TEI/editions/869-33-14.xml","TEI/editions/848-20-49.xml","TEI/editions/848-21-41.xml","TEI/editions/852-25-42.xml","TEI/editions/869-33-12.xml","TEI/editions/869-33-16.xml","TEI/editions/848-20-71.xml","TEI/editions/869-33-51.xml","TEI/editions/869-33-15.xml","TEI/editions/852-23-73.xml","TEI/editions/852-25-44.xml","TEI/editions/869-33-41.xml","TEI/editions/848-20-46.xml","TEI/editions/852-25-43.xml","TEI/meta/about.xml","TEI/editions/852-25-47.xml","TEI/editions/822-16-24.xml","TEI/editions/869-33-42.xml","TEI/editions/869-33-13.xml","TEI/editions/848-20-48.xml","TEI/editions/822-15-28.xml","TEI/editions/869-33-38.xml","TEI/editions/869-33-46.xml","TEI/editions/852-23-69.xml","TEI/editions/869-33-35.xml","TEI/editions/869-33-65.xml","TEI/editions/852-25-75.xml","TEI/editions/869-33-11.xml","TEI/editions/822-16-11.xml","TEI/editions/869-33-50.xml","TEI/editions/848-21-40.xml","TEI/editions/869-33-37.xml","TEI/editions/869-33-36.xml"],"langs":[]}